main.py
libreria_hola_marco-0.1.1.dist-info/METADATA
libreria_hola_marco-0.1.1.dist-info/WHEEL
libreria_hola_marco-0.1.1.dist-info/top_level.txt
libreria_hola_marco-0.1.1.dist-info/RECORD
