Metadata-Version: 2.4
Name: libreria-hola-marco
Version: 0.1.1
Summary: Librería con la que Marco te saluda
Requires-Python: >=3.13
